{
  "hash": "515b2225",
  "configHash": "72a40be6",
  "lockfileHash": "5107417d",
  "browserHash": "b0fbc669",
  "optimized": {
    "react/jsx-dev-runtime": {
      "src": "../../node_modules/react/jsx-dev-runtime.js",
      "file": "react_jsx-dev-runtime.js",
      "fileHash": "99db5c46",
      "needsInterop": true
    },
    "react": {
      "src": "../../node_modules/react/index.js",
      "file": "react.js",
      "fileHash": "ebe30e87",
      "needsInterop": true
    },
    "react-dom/client": {
      "src": "../../node_modules/react-dom/client.js",
      "file": "react-dom_client.js",
      "fileHash": "13ef5332",
      "needsInterop": true
    }
  },
  "chunks": {
    "chunk-TDVGPZLM": {
      "file": "chunk-TDVGPZLM.js"
    }
  }
}